sofa/__init__.py
sofa/_database.py
sofa/access/__init__.py
sofa/access/dimensions.py
sofa/access/metadata.py
sofa/access/proxy.py
sofa/access/variables.py
sofa/conventions/GeneralFIR.py
sofa/conventions/GeneralFIRE.py
sofa/conventions/GeneralTF.py
sofa/conventions/MultiSpeakerBRIR.py
sofa/conventions/SimpleFreeFieldHRIR.py
sofa/conventions/SimpleFreeFieldSOS.py
sofa/conventions/SimpleFreeFieldTF.py
sofa/conventions/SimpleHeadphoneIR.py
sofa/conventions/SingleRoomDRIR.py
sofa/conventions/__init__.py
sofa/conventions/base.py
sofa/datatypes/FIR.py
sofa/datatypes/FIRE.py
sofa/datatypes/SOS.py
sofa/datatypes/TF.py
sofa/datatypes/__init__.py
sofa/datatypes/base.py
sofa/roomtypes/__init__.py
sofa/roomtypes/base.py
sofa/roomtypes/freefield.py
sofa/roomtypes/reverberant.py
sofa/roomtypes/shoebox.py
sofa/spatial/__init__.py
sofa/spatial/coordinates.py
sofa/spatial/spatialobject.py
python_sofa-0.2.0.dist-info/LICENSE
python_sofa-0.2.0.dist-info/METADATA
python_sofa-0.2.0.dist-info/WHEEL
python_sofa-0.2.0.dist-info/top_level.txt
python_sofa-0.2.0.dist-info/zip-safe
python_sofa-0.2.0.dist-info/RECORD
