Metadata-Version: 2.1
Name: python-sofa
Version: 0.2.0
Summary: Python SOFA API
Home-page: http://github.com/spatialaudio/python-sofa/
Author: Jannika Lossner
Author-email: jnlossner@gmail.com
License: MIT
Keywords: audio,SOFA,acoustics
Platform: any
Classifier: Development Status :: 3 - Alpha
Classifier: License :: OSI Approved :: MIT License
Classifier: Operating System :: OS Independent
Classifier: Programming Language :: Python
Classifier: Programming Language :: Python :: 3
Classifier: Programming Language :: Python :: 3.5
Classifier: Programming Language :: Python :: 3.6
Classifier: Programming Language :: Python :: 3.7
Classifier: Programming Language :: Python :: 3 :: Only
Classifier: Topic :: Scientific/Engineering
Requires-Python: >=3.5
Requires-Dist: numpy
Requires-Dist: scipy (>=1.2.0)
Requires-Dist: netcdf4
Requires-Dist: datetime
